Nasiwak/__init__.py
Nasiwak/aisys.py
Nasiwak/bot_update.py
Nasiwak/creater.py
Nasiwak/maildealer.py
Nasiwak/sharepoint.py
Nasiwak/webaccess.py
Nasiwak-0.1.9.dist-info/METADATA
Nasiwak-0.1.9.dist-info/WHEEL
Nasiwak-0.1.9.dist-info/top_level.txt
Nasiwak-0.1.9.dist-info/RECORD
