Metadata-Version: 2.1
Name: Nasiwak
Version: 0.1.9
Summary: A model that contains all the needs of Nasiwak Company Developers
Author: Nasiwak Team
Author-email: Kushalnasiwak@outlook.com
License: MIT
Requires-Dist: selenium>=4.26.0
Requires-Dist: pyautogui>=0.9.54
